calculator.sv
`timescale 1ns / 1ps

module calculator(
	input logic target,
	input logic top,
	input logic top_right,
	input logic right,
	input logic bottom_right,
	input logic bottom,
	input logic bottom_left,
	input logic left,
	input logic top_left,

	output logic target_next
);

logic [2:0] count;	// Count of live neighbors;

always_comb begin
	count = 0;
	if (top) count++;
	if (top_right) count++;
	if (right) count++;
	if (bottom_right) count++;
	if (bottom) count++;
	if (bottom_left) count++;
	if (left) count++;
	if (top_left) count++;
end

// The rules of Conway's Game of Life
always_comb begin
	if (target) begin
		if (count == 2 || count == 3) target_next = 1;
		else target_next = 0;
	end else begin
		if (count == 3) target_next = 1;
		else target_next = 0;
	end
end

endmodule

rtl/conway.sv
`timescale 1ns / 1ps

module conway(	
	input logic clk,		// clock signal
	input logic rst,		// reset signal
	input logic state,		// 0 = load, 1 = run
	input logic [15:0]addr,	// address for loading the grid

	output logic next_gen	// output signal to indicate next generation

);

// logic [255:0] mem[255:0];	// 256x256 memory for the grid
// logic [255:0] mem_next[255:0];	// 256x256 memory for the next generation

logic [255:0] mem[0:255];	// 256x256 memory for the grid
logic [255:0] mem_next[0:255];	// 256x256 memory for the next generation

initial begin
	 for (int i = 0; i < 255; i++) begin
		// Initialize the memory to zeroes
		for (int j = 0; j < 255; j++) begin
			mem[i][j] = 0;
		end
	 end
end

logic [7:0] row = 0;
logic [7:0] col = 0;

logic pixel1;
logic pixel2;
logic pixel3;
logic pixel4;
logic pixel5;
logic pixel6;
logic pixel7;
logic pixel8;
logic pixel9;
logic pixel10;
logic pixel11;
logic pixel12;
logic pixel13;
logic pixel14;
logic pixel15;
logic pixel16;


always_ff @(posedge clk) begin
	next_gen <= 0;	// Reset next_gen at the start of each clock cycle

	mem_next[row][col] <= pixel1;
	mem_next[row][col+1] <= pixel2;
	mem_next[row][col+2] <= pixel3;
	mem_next[row][col+3] <= pixel4;
	mem_next[row][col+4] <= pixel5;
	mem_next[row][col+5] <= pixel6;
	mem_next[row][col+6] <= pixel7;
	mem_next[row][col+7] <= pixel8;
	mem_next[row][col+8] <= pixel9;
	mem_next[row][col+9] <= pixel10;
	mem_next[row][col+10] <= pixel11;
	mem_next[row][col+11] <= pixel12;
	mem_next[row][col+12] <= pixel13;
	mem_next[row][col+13] <= pixel14;
	mem_next[row][col+14] <= pixel15;
	mem_next[row][col+15] <= pixel16;
	
	if (rst) begin
		for (int i = 0; i < 256; i++) begin
			for (int j = 0; j < 256; j++) begin
				mem[i][j] <= 0;
			end
		end
	end
	if (!state) mem[addr[15:8]][addr[7:0]] <= 1;

	else begin
		if (col == 0 && row == 0) begin
			$writememb("mem.txt", mem);	// Write memory to file
		end
		if (col >= 239) begin			// If we are at the end of a row
			col <= 0;					// Reset column to 0
			if (row == 255) begin		// If we are at the end of the grid
				row <= 0;				// Reset row to 0
				mem <= mem_next;		// Update the memory with the next generation
				next_gen <= 1;			// Set next_gen to 1 to indicate the next generation is ready
			end else begin
				row <= row + 1;			// Move to the next row
			end
		end else begin
			col <= col + 16;			// Move to the next set of columns
		end
	end




end

// holy """parallelism""" batman
calculator calc1(
		.target(mem[row][col]),
		.top(mem[row-1][col]),
		.top_right(mem[row-1][col+1]),
		.right(mem[row][col+1]),
		.bottom_right(mem[row+1][col+1]),
		.bottom(mem[row+1][col]),
		.bottom_left(mem[row+1][col-1]),
		.left(mem[row][col-1]),
		.top_left(mem[row-1][col-1]),
		.target_next(pixel1)
	);

	calculator calc2(
		.target(mem[row][col+1]),
		.top(mem[row-1][col+1]),
		.top_right(mem[row-1][col+2]),
		.right(mem[row][col+2]),
		.bottom_right(mem[row+1][col+2]),
		.bottom(mem[row+1][col+1]),
		.bottom_left(mem[row+1][col]),
		.left(mem[row][col]),
		.top_left(mem[row-1][col]),
		.target_next(pixel2)
	);

	calculator calc3(
		.target(mem[row][col+2]),
		.top(mem[row-1][col+2]),
		.top_right(mem[row-1][col+3]),
		.right(mem[row][col+3]),
		.bottom_right(mem[row+1][col+3]),
		.bottom(mem[row+1][col+2]),
		.bottom_left(mem[row+1][col+1]),
		.left(mem[row][col+1]),
		.top_left(mem[row-1][col+1]),
		.target_next(pixel3)
	);

	calculator calc4(
		.target(mem[row][col+3]),
		.top(mem[row-1][col+3]),
		.top_right(mem[row-1][col+4]),
		.right(mem[row][col+4]),
		.bottom_right(mem[row+1][col+4]),
		.bottom(mem[row+1][col+3]),
		.bottom_left(mem[row+1][col+2]),
		.left(mem[row][col+2]),
		.top_left(mem[row-1][col+2]),
		.target_next(pixel4)
	);

	calculator calc5(
		.target(mem[row][col+4]),
		.top(mem[row-1][col+4]),
		.top_right(mem[row-1][col+5]),
		.right(mem[row][col+5]),
		.bottom_right(mem[row+1][col+5]),
		.bottom(mem[row+1][col+4]),
		.bottom_left(mem[row+1][col+3]),
		.left(mem[row][col+3]),
		.top_left(mem[row-1][col+3]),
		.target_next(pixel5)
	);

	calculator calc6(
		.target(mem[row][col+5]),
		.top(mem[row-1][col+5]),
		.top_right(mem[row-1][col+6]),
		.right(mem[row][col+6]),
		.bottom_right(mem[row+1][col+6]),
		.bottom(mem[row+1][col+5]),
		.bottom_left(mem[row+1][col+4]),
		.left(mem[row][col+4]),
		.top_left(mem[row-1][col+4]),
		.target_next(pixel6)
	);

	calculator calc7(
		.target(mem[row][col+6]),
		.top(mem[row-1][col+6]),
		.top_right(mem[row-1][col+7]),
		.right(mem[row][col+7]),
		.bottom_right(mem[row+1][col+7]),
		.bottom(mem[row+1][col+6]),
		.bottom_left(mem[row+1][col+5]),
		.left(mem[row][col+5]),
		.top_left(mem[row-1][col+5]),
		.target_next(pixel7)
	);

	calculator calc8(
		.target(mem[row][col+7]),
		.top(mem[row-1][col+7]),
		.top_right(mem[row-1][col+8]),
		.right(mem[row][col+8]),
		.bottom_right(mem[row+1][col+8]),
		.bottom(mem[row+1][col+7]),
		.bottom_left(mem[row+1][col+6]),
		.left(mem[row][col+6]),
		.top_left(mem[row-1][col+6]),
		.target_next(pixel8)
	);

	calculator calc9(
		.target(mem[row][col+8]),
		.top(mem[row-1][col+8]),
		.top_right(mem[row-1][col+9]),
		.right(mem[row][col+9]),
		.bottom_right(mem[row+1][col+9]),
		.bottom(mem[row+1][col+8]),
		.bottom_left(mem[row+1][col+7]),
		.left(mem[row][col+7]),
		.top_left(mem[row-1][col+7]),
		.target_next(pixel9)
	);

	calculator calc10(
		.target(mem[row][col+9]),
		.top(mem[row-1][col+9]),
		.top_right(mem[row-1][col+10]),
		.right(mem[row][col+10]),
		.bottom_right(mem[row+1][col+10]),
		.bottom(mem[row+1][col+9]),
		.bottom_left(mem[row+1][col+8]),
		.left(mem[row][col+8]),
		.top_left(mem[row-1][col+8]),
		.target_next(pixel10)
	);

	calculator calc11(
		.target(mem[row][col+10]),
		.top(mem[row-1][col+10]),
		.top_right(mem[row-1][col+11]),
		.right(mem[row][col+11]),
		.bottom_right(mem[row+1][col+11]),
		.bottom(mem[row+1][col+10]),
		.bottom_left(mem[row+1][col+9]),
		.left(mem[row][col+9]),
		.top_left(mem[row-1][col+9]),
		.target_next(pixel11)
	);

	calculator calc12(
		.target(mem[row][col+11]),
		.top(mem[row-1][col+11]),
		.top_right(mem[row-1][col+12]),
		.right(mem[row][col+12]),
		.bottom_right(mem[row+1][col+12]),
		.bottom(mem[row+1][col+11]),
		.bottom_left(mem[row+1][col+10]),
		.left(mem[row][col+10]),
		.top_left(mem[row-1][col+10]),
		.target_next(pixel12)
	);

	calculator calc13(
		.target(mem[row][col+12]),
		.top(mem[row-1][col+12]),
		.top_right(mem[row-1][col+13]),
		.right(mem[row][col+13]),
		.bottom_right(mem[row+1][col+13]),
		.bottom(mem[row+1][col+12]),
		.bottom_left(mem[row+1][col+11]),
		.left(mem[row][col+11]),
		.top_left(mem[row-1][col+11]),
		.target_next(pixel13)
	);

	calculator calc14(
		.target(mem[row][col+13]),
		.top(mem[row-1][col+13]),
		.top_right(mem[row-1][col+14]),
		.right(mem[row][col+14]),
		.bottom_right(mem[row+1][col+14]),
		.bottom(mem[row+1][col+13]),
		.bottom_left(mem[row+1][col+12]),
		.left(mem[row][col+12]),
		.top_left(mem[row-1][col+12]),
		.target_next(pixel14)
	);

	calculator calc15(
		.target(mem[row][col+14]),
		.top(mem[row-1][col+14]),
		.top_right(mem[row-1][col+15]),
		.right(mem[row][col+15]),
		.bottom_right(mem[row+1][col+15]),
		.bottom(mem[row+1][col+14]),
		.bottom_left(mem[row+1][col+13]),
		.left(mem[row][col+13]),
		.top_left(mem[row-1][col+13]),
		.target_next(pixel15)
	);

	calculator calc16(
		.target(mem[row][col+15]),
		.top(mem[row-1][col+15]),
		.top_right(mem[row-1][col+16]),
		.right(mem[row][col+16]),
		.bottom_right(mem[row+1][col+16]),
		.bottom(mem[row+1][col+15]),
		.bottom_left(mem[row+1][col+14]),
		.left(mem[row][col+14]),
		.top_left(mem[row-1][col+14]),
		.target_next(pixel16)
	);

endmodule

tests/conway_tb/conway_tb.sv
`timescale 1ns / 1ps

module conway_tb;

    // Signals
    logic clk;
    logic rst;

    logic state;		// 0 = load, 1 = run
    logic [15:0] addr;

	logic next_gen;

    // Unit Under Test
    conway #(
    ) uut (
        .clk(clk),
        .rst(rst),
        .state(state),
        .addr(addr),
		.next_gen(next_gen)
    );

    // Clock generation
    initial begin
        clk = 0;
        forever #5 clk = ~clk; // 100 MHz clock
    end

	initial begin
    // Name as needed
    $dumpfile("tb_conway.vcd");
    $dumpvars(0);
end

    // Testbench logic
    initial begin
        // Initialize signals
        rst = 1;
        state = 0;
		

        // Reset the UUT
        #10 rst = 0;

        // Add stimulus here
        // simple glider design found on google
		addr = 16'h02ff; // Load address
		#10;
		addr = 16'h01fd; // Load address
		#10;
		addr = 16'h02fd; // Load address
		#10;
		addr = 16'h03fd; // Load address
		#10;
		addr = 16'h03fe; // Load address
		#10;
        state = 1; // Start running
		#20

		// for (logic [7:0] i = 0; i <= 8'd0; i++) begin
		// 	wait(next_gen == 1);		// generation 1
		// 	$display("Generation %0d", i);
		//  	#20;
		// end

		 wait(next_gen == 1);		// generation 1
		 #20;
		 wait(next_gen == 1); 		// generation 2
		 #20;
		//  wait(next_gen == 1);		// generation 3
		//  #20;
		//  wait(next_gen == 1);		// generation 4
		//  #20;
        $finish;
    end

endmodule

tests/conway_tb/tb_.vcd
$version Generated by VerilatedVcd $end
$timescale 1ps $end
 $scope module $rootio $end
 $upscope $end
 $scope module conway_tb $end
  $var wire 1 ~ clk $end
  $var wire 1 !! rst $end
  $var wire 1 "! state $end
  $var wire 16 #! addr [15:0] $end
  $var wire 1 ) next_gen $end
  $scope module uut $end
   $var wire 1 ~ clk $end
   $var wire 1 !! rst $end
   $var wire 1 "! state $end
   $var wire 16 #! addr [15:0] $end
   $var wire 1 ) next_gen $end
   $var wire 8 * row [7:0] $end
   $var wire 8 + col [7:0] $end
   $scope module calc1 $end
    $var wire 1 , target $end
    $var wire 1 - top $end
    $var wire 1 . top_right $end
    $var wire 1 / right $end
    $var wire 1 0 bottom_right $end
    $var wire 1 1 bottom $end
    $var wire 1 # bottom_left $end
    $var wire 1 $ left $end
    $var wire 1 % top_left $end
    $var wire 1 2 target_next $end
    $var wire 3 3 count [2:0] $end
   $upscope $end
   $scope module calc10 $end
    $var wire 1 4 target $end
    $var wire 1 5 top $end
    $var wire 1 6 top_right $end
    $var wire 1 7 right $end
    $var wire 1 8 bottom_right $end
    $var wire 1 9 bottom $end
    $var wire 1 : bottom_left $end
    $var wire 1 ; left $end
    $var wire 1 < top_left $end
    $var wire 1 = target_next $end
    $var wire 3 > count [2:0] $end
   $upscope $end
   $scope module calc11 $end
    $var wire 1 7 target $end
    $var wire 1 6 top $end
    $var wire 1 ? top_right $end
    $var wire 1 @ right $end
    $var wire 1 A bottom_right $end
    $var wire 1 8 bottom $end
    $var wire 1 9 bottom_left $end
    $var wire 1 4 left $end
    $var wire 1 5 top_left $end
    $var wire 1 B target_next $end
    $var wire 3 C count [2:0] $end
   $upscope $end
   $scope module calc12 $end
    $var wire 1 @ target $end
    $var wire 1 ? top $end
    $var wire 1 D top_right $end
    $var wire 1 E right $end
    $var wire 1 F bottom_right $end
    $var wire 1 A bottom $end
    $var wire 1 8 bottom_left $end
    $var wire 1 7 left $end
    $var wire 1 6 top_left $end
    $var wire 1 G target_next $end
    $var wire 3 H count [2:0] $end
   $upscope $end
   $scope module calc13 $end
    $var wire 1 E target $end
    $var wire 1 D top $end
    $var wire 1 I top_right $end
    $var wire 1 J right $end
    $var wire 1 K bottom_right $end
    $var wire 1 F bottom $end
    $var wire 1 A bottom_left $end
    $var wire 1 @ left $end
    $var wire 1 ? top_left $end
    $var wire 1 L target_next $end
    $var wire 3 M count [2:0] $end
   $upscope $end
   $scope module calc14 $end
    $var wire 1 J target $end
    $var wire 1 I top $end
    $var wire 1 N top_right $end
    $var wire 1 O right $end
    $var wire 1 P bottom_right $end
    $var wire 1 K bottom $end
    $var wire 1 F bottom_left $end
    $var wire 1 E left $end
    $var wire 1 D top_left $end
    $var wire 1 Q target_next $end
    $var wire 3 R count [2:0] $end
   $upscope $end
   $scope module calc15 $end
    $var wire 1 O target $end
    $var wire 1 N top $end
    $var wire 1 S top_right $end
    $var wire 1 T right $end
    $var wire 1 U bottom_right $end
    $var wire 1 P bottom $end
    $var wire 1 K bottom_left $end
    $var wire 1 J left $end
    $var wire 1 I top_left $end
    $var wire 1 V target_next $end
    $var wire 3 W count [2:0] $end
   $upscope $end
   $scope module calc16 $end
    $var wire 1 T target $end
    $var wire 1 S top $end
    $var wire 1 & top_right $end
    $var wire 1 ' right $end
    $var wire 1 ( bottom_right $end
    $var wire 1 U bottom $end
    $var wire 1 P bottom_left $end
    $var wire 1 O left $end
    $var wire 1 N top_left $end
    $var wire 1 X target_next $end
    $var wire 3 Y count [2:0] $end
   $upscope $end
   $scope module calc2 $end
    $var wire 1 / target $end
    $var wire 1 . top $end
    $var wire 1 Z top_right $end
    $var wire 1 [ right $end
    $var wire 1 \ bottom_right $end
    $var wire 1 0 bottom $end
    $var wire 1 1 bottom_left $end
    $var wire 1 , left $end
    $var wire 1 - top_left $end
    $var wire 1 ] target_next $end
    $var wire 3 ^ count [2:0] $end
   $upscope $end
   $scope module calc3 $end
    $var wire 1 [ target $end
    $var wire 1 Z top $end
    $var wire 1 _ top_right $end
    $var wire 1 ` right $end
    $var wire 1 a bottom_right $end
    $var wire 1 \ bottom $end
    $var wire 1 0 bottom_left $end
    $var wire 1 / left $end
    $var wire 1 . top_left $end
    $var wire 1 b target_next $end
    $var wire 3 c count [2:0] $end
   $upscope $end
   $scope module calc4 $end
    $var wire 1 ` target $end
    $var wire 1 _ top $end
    $var wire 1 d top_right $end
    $var wire 1 e right $end
    $var wire 1 f bottom_right $end
    $var wire 1 a bottom $end
    $var wire 1 \ bottom_left $end
    $var wire 1 [ left $end
    $var wire 1 Z top_left $end
    $var wire 1 g target_next $end
    $var wire 3 h count [2:0] $end
   $upscope $end
   $scope module calc5 $end
    $var wire 1 e target $end
    $var wire 1 d top $end
    $var wire 1 i top_right $end
    $var wire 1 j right $end
    $var wire 1 k bottom_right $end
    $var wire 1 f bottom $end
    $var wire 1 a bottom_left $end
    $var wire 1 ` left $end
    $var wire 1 _ top_left $end
    $var wire 1 l target_next $end
    $var wire 3 m count [2:0] $end
   $upscope $end
   $scope module calc6 $end
    $var wire 1 j target $end
    $var wire 1 i top $end
    $var wire 1 n top_right $end
    $var wire 1 o right $end
    $var wire 1 p bottom_right $end
    $var wire 1 k bottom $end
    $var wire 1 f bottom_left $end
    $var wire 1 e left $end
    $var wire 1 d top_left $end
    $var wire 1 q target_next $end
    $var wire 3 r count [2:0] $end
   $upscope $end
   $scope module calc7 $end
    $var wire 1 o target $end
    $var wire 1 n top $end
    $var wire 1 s top_right $end
    $var wire 1 t right $end
    $var wire 1 u bottom_right $end
    $var wire 1 p bottom $end
    $var wire 1 k bottom_left $end
    $var wire 1 j left $end
    $var wire 1 i top_left $end
    $var wire 1 v target_next $end
    $var wire 3 w count [2:0] $end
   $upscope $end
   $scope module calc8 $end
    $var wire 1 t target $end
    $var wire 1 s top $end
    $var wire 1 < top_right $end
    $var wire 1 ; right $end
    $var wire 1 : bottom_right $end
    $var wire 1 u bottom $end
    $var wire 1 p bottom_left $end
    $var wire 1 o left $end
    $var wire 1 n top_left $end
    $var wire 1 x target_next $end
    $var wire 3 y count [2:0] $end
   $upscope $end
   $scope module calc9 $end
    $var wire 1 ; target $end
    $var wire 1 < top $end
    $var wire 1 5 top_right $end
    $var wire 1 4 right $end
    $var wire 1 9 bottom_right $end
    $var wire 1 : bottom $end
    $var wire 1 u bottom_left $end
    $var wire 1 t left $end
    $var wire 1 s top_left $end
    $var wire 1 z target_next $end
    $var wire 3 { count [2:0] $end
   $upscope $end
   $scope module unnamedblk1 $end
    $var wire 32 $! i [31:0] $end
    $scope module unnamedblk2 $end
     $var wire 32 %! j [31:0] $end
    $upscope $end
   $upscope $end
   $scope module unnamedblk3 $end
    $var wire 32 | i [31:0] $end
    $scope module unnamedblk4 $end
     $var wire 32 } j [31:0] $end
    $upscope $end
   $upscope $end
  $upscope $end
 $upscope $end
$enddefinitions $end


#0
0#
0$
0%
0&
0'
0(
0)
b00000000 *
b00000000 +
0,
0-
0.
0/
00
01
02
b000 3
04
05
06
07
08
09
0:
0;
0<
0=
b000 >
0?
0@
0A
0B
b000 C
0D
0E
0F
0G
b000 H
0I
0J
0K
0L
b000 M
0N
0O
0P
0Q
b000 R
0S
0T
0U
0V
b000 W
0X
b000 Y
0Z
0[
0\
0]
b000 ^
0_
0`
0a
0b
b000 c
0d
0e
0f
0g
b000 h
0i
0j
0k
0l
b000 m
0n
0o
0p
0q
b000 r
0s
0t
0u
0v
b000 w
0x
b000 y
0z
b000 {
b00000000000000000000000000000000 |
b00000000000000000000000000000000 }
0~
1!!
0"!
b0000000000000000 #!
b00000000000000000000000011111111 $!
b00000000000000000000000011111111 %!
#5000
1,
b001 ^
b00000000000000000000000100000000 |
b00000000000000000000000100000000 }
1~
#10000
0~
0!!
b0000001011111111 #!
#15000
1~
#20000
0~
b0000000111111101 #!
#25000
1~
#30000
0~
b0000001011111101 #!
#35000
1~
#40000
0~
b0000001111111101 #!
#45000
1~
#50000
0~
b0000001111111110 #!
#55000
1~
#60000
0~
1"!
#65000
b00010000 +
0,
b000 ^
1~
#70000
0~
#75000
b00100000 +
1~
#80000
0~
#85000
b00110000 +
1~
#90000
0~
#95000
b01000000 +
1~
#100000
0~
#105000
b01010000 +
1~
#110000
0~
#115000
b01100000 +
1~
#120000
0~
#125000
b01110000 +
1~
#130000
0~
#135000
b10000000 +
1~
#140000
0~
#145000
b10010000 +
1~
#150000
0~
#155000
b10100000 +
1~
#160000
0~
#165000
b10110000 +
1~
#170000
0~
#175000
b11000000 +
1~
#180000
0~
#185000
b11010000 +
1~
#190000
0~
#195000
b11100000 +
1~
#200000
0~
#205000
1'
b11110000 +
1K
b001 M
b001 R
b001 W
b001 Y
1~
#210000
0~
#215000
1#
0'
b00000001 *
b00000000 +
1-
b010 3
0K
b000 M
b000 R
b000 W
b000 Y
b001 ^
1~
#220000
0~
#225000
0#
b00010000 +
0-
b000 3
b000 ^
1~
#230000
0~
#235000
b00100000 +
1~
#240000
0~
#245000
b00110000 +
1~
#250000
0~
#255000
b01000000 +
1~
#260000
0~
#265000
b01010000 +
1~
#270000
0~
#275000
b01100000 +
1~
#280000
0~
#285000
b01110000 +
1~
#290000
0~
#295000
b10000000 +
1~
#300000
0~
#305000
b10010000 +
1~
#310000
0~
#315000
b10100000 +
1~
#320000
0~
#325000
b10110000 +
1~
#330000
0~
#335000
b11000000 +
1~
#340000
0~
#345000
b11010000 +
1~
#350000
0~
#355000
b11100000 +
1~
#360000
0~
#365000
1&
b11110000 +
1J
1K
b010 M
b001 R
1U
1V
b011 W
b010 Y
1~
#370000
0~
#375000
1$
0&
b00000010 *
b00000000 +
b001 3
0J
0K
b000 M
b000 R
0U
0V
b000 W
b000 Y
1~
#380000
0~
#385000
0$
b00010000 +
b000 3
1~
#390000
0~
#395000
b00100000 +
1~
#400000
0~
#405000
b00110000 +
1~
#410000
0~
#415000
b01000000 +
1~
#420000
0~
#425000
b01010000 +
1~
#430000
0~
#435000
b01100000 +
1~
#440000
0~
#445000
b01110000 +
1~
#450000
0~
#455000
b10000000 +
1~
#460000
0~
#465000
b10010000 +
1~
#470000
0~
#475000
b10100000 +
1~
#480000
0~
#485000
b10110000 +
1~
#490000
0~
#495000
b11000000 +
1~
#500000
0~
#505000
b11010000 +
1~
#510000
0~
#515000
b11100000 +
1~
#520000
0~
#525000
b11110000 +
1I
1J
1K
1L
b011 M
1P
1Q
b011 R
1T
b101 W
b001 Y
1~
#530000
0~
#535000
1%
b00000011 *
b00000000 +
b001 3
0I
0J
0K
0L
b000 M
0P
0Q
b000 R
0T
b000 W
b000 Y
1~
#540000
0~
#545000
0%
b00010000 +
b000 3
1~
#550000
0~
#555000
b00100000 +
1~
#560000
0~
#565000
b00110000 +
1~
#570000
0~
#575000
b01000000 +
1~
#580000
0~
#585000
b01010000 +
1~
#590000
0~
#595000
b01100000 +
1~
#600000
0~
#605000
b01110000 +
1~
#610000
0~
#615000
b10000000 +
1~
#620000
0~
#625000
b10010000 +
1~
#630000
0~
#635000
b10100000 +
1~
#640000
0~
#645000
b10110000 +
1~
#650000
0~
#655000
b11000000 +
1~
#660000
0~
#665000
b11010000 +
1~
#670000
0~
#675000
b11100000 +
1~
#680000
0~
#685000
b11110000 +
1I
1J
b010 M
1O
1Q
b010 R
1S
1V
b011 W
b010 Y
1~
#690000
0~
#695000
b00000100 *
b00000000 +
0I
0J
b000 M
0O
0Q
b000 R
0S
0V
b000 W
b000 Y
1~
#700000
0~
#705000
b00010000 +
1~
#710000
0~
#715000
b00100000 +
1~
#720000
0~
#725000
b00110000 +
1~
#730000
0~
#735000
b01000000 +
1~
#740000
0~
#745000
b01010000 +
1~
#750000
0~
#755000
b01100000 +
1~
#760000
0~
#765000
b01110000 +
1~
#770000
0~
#775000
b10000000 +
1~
#780000
0~
#785000
b10010000 +
1~
#790000
0~
#795000
b10100000 +
1~
#800000
0~
#805000
b10110000 +
1~
#810000
0~
#815000
b11000000 +
1~
#820000
0~
#825000
b11010000 +
1~
#830000
0~
#835000
b11100000 +
1~
#840000
0~
#845000
b11110000 +
1I
b001 M
1N
b010 R
b010 W
b001 Y
1~
#850000
0~
#855000
b00000101 *
b00000000 +
0I
b000 M
0N
b000 R
b000 W
b000 Y
1~
#860000
0~
#865000
b00010000 +
1~
#870000
0~
#875000
b00100000 +
1~
#880000
0~
#885000
b00110000 +
1~
#890000
0~
#895000
b01000000 +
1~
#900000
0~
#905000
b01010000 +
1~
#910000
0~
#915000
b01100000 +
1~
#920000
0~
#925000
b01110000 +
1~
#930000
0~
#935000
b10000000 +
1~
#940000
0~
#945000
b10010000 +
1~
#950000
0~
#955000
b10100000 +
1~
#960000
0~
#965000
b10110000 +
1~
#970000
0~
#975000
b11000000 +
1~
#980000
0~
#985000
b11010000 +
1~
#990000
0~
#995000
b11100000 +
1~
#1000000
0~
#1005000
b11110000 +
1~
#1010000
0~
#1015000
b00000110 *
b00000000 +
1~
#1020000
0~
#1025000
b00010000 +
1~
#1030000
0~
#1035000
b00100000 +
1~
#1040000
0~
#1045000
b00110000 +
1~
#1050000
0~
#1055000
b01000000 +
1~
#1060000
0~
#1065000
b01010000 +
1~
#1070000
0~
#1075000
b01100000 +
1~
#1080000
0~
#1085000
b01110000 +
1~
#1090000
0~
#1095000
b10000000 +
1~
#1100000
0~
#1105000
b10010000 +
1~
#1110000
0~
#1115000
b10100000 +
1~
#1120000
0~
#1125000
b10110000 +
1~
#1130000
0~
#1135000
b11000000 +
1~
#1140000
0~
#1145000
b11010000 +
1~
#1150000
0~
#1155000
b11100000 +
1~
#1160000
0~
#1165000
b11110000 +
1~
#1170000
0~
#1175000
b00000111 *
b00000000 +
1~
#1180000
0~
#1185000
b00010000 +
1~
#1190000
0~
#1195000
b00100000 +
1~
#1200000
0~
#1205000
b00110000 +
1~
#1210000
0~
#1215000
b01000000 +
1~
#1220000
0~
#1225000
b01010000 +
1~
#1230000
0~
#1235000
b01100000 +
1~
#1240000
0~
#1245000
b01110000 +
1~
#1250000
0~
#1255000
b10000000 +
1~
#1260000
0~
#1265000
b10010000 +
1~
#1270000
0~
#1275000
b10100000 +
1~
#1280000
0~
#1285000
b10110000 +
1~
#1290000
0~
#1295000
b11000000 +
1~
#1300000
0~
#1305000
b11010000 +
1~
#1310000
0~
#1315000
b11100000 +
1~
#1320000
0~
#1325000
b11110000 +
1~
#1330000
0~
#1335000
b00001000 *
b00000000 +
1~
#1340000
0~
#1345000
b00010000 +
1~
#1350000
0~
#1355000
b00100000 +
1~
#1360000
0~
#1365000
b00110000 +
1~
#1370000
0~
#1375000
b01000000 +
1~
#1380000
0~
#1385000
b01010000 +
1~
#1390000
0~
#1395000
b01100000 +
1~
#1400000
0~
#1405000
b01110000 +
1~
#1410000
0~
#1415000
b10000000 +
1~
#1420000
0~
#1425000
b10010000 +
1~
#1430000
0~
#1435000
b10100000 +
1~
#1440000
0~
#1445000
b10110000 +
1~
#1450000
0~
#1455000
b11000000 +
1~
#1460000
0~
#1465000
b11010000 +
1~
#1470000
0~
#1475000
b11100000 +
1~
#1480000
0~
#1485000
b11110000 +
1~
#1490000
0~
#1495000
b00001001 *
b00000000 +
1~
#1500000
0~
#1505000
b00010000 +
1~
#1510000
0~
#1515000
b00100000 +
1~
#1520000
0~
#1525000
b00110000 +
1~
#1530000
0~
#1535000
b01000000 +
1~
#1540000
0~
#1545000
b01010000 +
1~
#1550000
0~
#1555000
b01100000 +
1~
#1560000
0~
#1565000
b01110000 +
1~
#1570000
0~
#1575000
b10000000 +
1~
#1580000
0~
#1585000
b10010000 +
1~
#1590000
0~
#1595000
b10100000 +
1~
#1600000
0~
#1605000
b10110000 +
1~
#1610000
0~
#1615000
b11000000 +
1~
#1620000
0~
#1625000
b11010000 +
1~
#1630000
0~
#1635000
b11100000 +
1~
#1640000
0~
#1645000
b11110000 +
1~
#1650000
0~
#1655000
b00001010 *
b00000000 +
1~
#1660000
0~
#1665000
b00010000 +
1~
#1670000
0~
#1675000
b00100000 +
1~
#1680000
0~
#1685000
b00110000 +
1~
#1690000
0~
#1695000
b01000000 +
1~
#1700000
0~
#1705000
b01010000 +
1~
#1710000
0~
#1715000
b01100000 +
1~
#1720000
0~
#1725000
b01110000 +
1~
#1730000
0~
#1735000
b10000000 +
1~
#1740000
0~
#1745000
b10010000 +
1~
#1750000
0~
#1755000
b10100000 +
1~
#1760000
0~
#1765000
b10110000 +
1~
#1770000
0~
#1775000
b11000000 +
1~
#1780000
0~
#1785000
b11010000 +
1~
#1790000
0~
#1795000
b11100000 +
1~
#1800000
0~
#1805000
b11110000 +
1~
#1810000
0~
#1815000
b00001011 *
b00000000 +
1~
#1820000
0~
#1825000
b00010000 +
1~
#1830000
0~
#1835000
b00100000 +
1~
#1840000
0~
#1845000
b00110000 +
1~
#1850000
0~
#1855000
b01000000 +
1~
#1860000
0~
#1865000
b01010000 +
1~
#1870000
0~
#1875000
b01100000 +
1~
#1880000
0~
#1885000
b01110000 +
1~
#1890000
0~
#1895000
b10000000 +
1~
#1900000
0~
#1905000
b10010000 +
1~
#1910000
0~
#1915000
b10100000 +
1~
#1920000
0~
#1925000
b10110000 +
1~
#1930000
0~
#1935000
b11000000 +
1~
#1940000
0~
#1945000
b11010000 +
1~
#1950000
0~
#1955000
b11100000 +
1~
#1960000
0~
#1965000
b11110000 +
1~
#1970000
0~
#1975000
b00001100 *
b00000000 +
1~
#1980000
0~
#1985000
b00010000 +
1~
#1990000
0~
#1995000
b00100000 +
1~
#2000000
0~
#2005000
b00110000 +
1~
#2010000
0~
#2015000
b01000000 +
1~
#2020000
0~
#2025000
b01010000 +
1~
#2030000
0~
#2035000
b01100000 +
1~
#2040000
0~
#2045000
b01110000 +
1~
#2050000
0~
#2055000
b10000000 +
1~
#2060000
0~
#2065000
b10010000 +
1~
#2070000
0~
#2075000
b10100000 +
1~
#2080000
0~
#2085000
b10110000 +
1~
#2090000
0~
#2095000
b11000000 +
1~
#2100000
0~
#2105000
b11010000 +
1~
#2110000
0~
#2115000
b11100000 +
1~
#2120000
0~
#2125000
b11110000 +
1~
#2130000
0~
#2135000
b00001101 *
b00000000 +
1~
#2140000
0~
#2145000
b00010000 +
1~
#2150000
0~
#2155000
b00100000 +
1~
#2160000
0~
#2165000
b00110000 +
1~
#2170000
0~
#2175000
b01000000 +
1~
#2180000
0~
#2185000
b01010000 +
1~
#2190000
0~
#2195000
b01100000 +
1~
#2200000
0~
#2205000
b01110000 +
1~
#2210000
0~
#2215000
b10000000 +
1~
#2220000
0~
#2225000
b10010000 +
1~
#2230000
0~
#2235000
b10100000 +
1~
#2240000
0~
#2245000
b10110000 +
1~
#2250000
0~
#2255000
b11000000 +
1~
#2260000
0~
#2265000
b11010000 +
1~
#2270000
0~
#2275000
b11100000 +
1~
#2280000
0~
#2285000
b11110000 +
1~
#2290000
0~
#2295000
b00001110 *
b00000000 +
1~
#2300000
0~
#2305000
b00010000 +
1~
#2310000
0~
#2315000
b00100000 +
1~
#2320000
0~
#2325000
b00110000 +
1~
#2330000
0~
#2335000
b01000000 +
1~
#2340000
0~
#2345000
b01010000 +
1~
#2350000
0~
#2355000
b01100000 +
1~
#2360000
0~
#2365000
b01110000 +
1~
#2370000
0~
#2375000
b10000000 +
1~
#2380000
0~
#2385000
b10010000 +
1~
#2390000
0~
#2395000
b10100000 +
1~
#2400000
0~
#2405000
b10110000 +
1~
#2410000
0~
#2415000
b11000000 +
1~
